{
  "post_stream": {
    "posts": [
      {
        "id": 13558,
        "name": "",
        "username": "uvatbc",
        "avatar_template": "https://avatars.discourse-cdn.com/v4/letter/u/e274bd/{size}.png",
        "created_at": "2023-11-29T22:30:12.375Z",
        "cooked": "<pre><code class=\"lang-auto\">In file included from /usr/include/fcntl.h:314,\n                 from /tmp/src/foundationdb/fdbbackup/FileDecoder.actor.cpp:28:\nIn function \u2018int open(const char*, int, ...)\u2019,\n    inlined from \u2018int file_converter::DecodeRangeProgress::OpenFileImplActor1State&lt;OpenFileImplActor1&gt;::a_body1cont2(const int&amp;, int) [with OpenFileImplActor1 = file_converter::DecodeRangeProgress::OpenFileImplActor1]\u2019 at /tmp/src/foundationdb/fdbbackup/FileDecoder.actor.cpp:690:20:\n/usr/include/x86_64-linux-gnu/bits/fcntl2.h:50:31: error: call to \u2018__open_missing_mode\u2019 declared with attribute error: open with O_CREAT or O_TMPFILE in second argument needs 3 arguments\n   50 |           __open_missing_mode ();\n      |           ~~~~~~~~~~~~~~~~~~~~^~\nninja: build stopped: subcommand failed.\n</code></pre>\n<p>Patch is very simple:</p>\n<pre><code class=\"lang-auto\">diff --git a/fdbbackup/FileDecoder.actor.cpp b/fdbbackup/FileDecoder.actor.cpp\nindex e69a1d370..c819d4f46 100644\n--- a/fdbbackup/FileDecoder.actor.cpp\n+++ b/fdbbackup/FileDecoder.actor.cpp\n@@ -687,7 +687,7 @@ public:\n                                }\n                        }\n\n-                       self-&gt;lfd = open(self-&gt;file.fileName.c_str(), O_WRONLY | O_CREAT | O_TRUNC);\n+                       self-&gt;lfd = open(self-&gt;file.fileName.c_str(), O_WRONLY | O_CREAT | O_TRUNC, 0600);\n                        if (self-&gt;lfd == -1) {\n                                TraceEvent(SevError, \"OpenLocalFileFailed\").detail(\"File\", self-&gt;file.fileName);\n                                throw platform_error();\n</code></pre>\n<p>I have the patch in <a href=\"https://github.com/uvatbc/foundationdb\" class=\"inline-onebox\" rel=\"noopener nofollow ugc\">GitHub - uvatbc/foundationdb: FoundationDB - the open source, distributed, transactional key-value store</a>, but I cannot create a PR because I am not in the list of contributors.</p>\n<p>Is there a contributor here who can take my patch and apply it to TOT?</p>\n<p>Thanks.</p>\n<p>Any pointers?</p>",
        "post_number": 1,
        "post_type": 1,
        "posts_count": 3,
        "updated_at": "2023-11-29T22:30:12.375Z",
        "reply_count": 0,
        "reply_to_post_number": null,
        "quote_count": 0,
        "incoming_link_count": 29,
        "reads": 10,
        "readers_count": 9,
        "score": 147.0,
        "yours": false,
        "topic_id": 4266,
        "topic_slug": "compilation-error-in-fdbbackup-filedecoder-actor-cpp",
        "display_username": "",
        "primary_group_name": null,
        "flair_name": null,
        "flair_url": null,
        "flair_bg_color": null,
        "flair_color": null,
        "flair_group_id": null,
        "badges_granted": [],
        "version": 1,
        "can_edit": false,
        "can_delete": false,
        "can_recover": false,
        "can_see_hidden_post": false,
        "can_wiki": false,
        "link_counts": [
          {
            "url": "https://github.com/uvatbc/foundationdb",
            "internal": false,
            "reflection": false,
            "title": "GitHub - uvatbc/foundationdb: FoundationDB - the open source, distributed, transactional key-value store",
            "clicks": 2
          }
        ],
        "read": true,
        "user_title": null,
        "bookmarked": false,
        "actions_summary": [],
        "moderator": false,
        "admin": false,
        "staff": false,
        "user_id": 1354,
        "hidden": false,
        "trust_level": 0,
        "deleted_at": null,
        "user_deleted": false,
        "edit_reason": null,
        "can_view_edit_history": true,
        "wiki": false,
        "post_url": "/t/compilation-error-in-fdbbackup-filedecoder-actor-cpp/4266/1",
        "can_accept_answer": false,
        "can_unaccept_answer": false,
        "accepted_answer": false,
        "topic_accepted_answer": null,
        "can_vote": false
      },
      {
        "id": 13559,
        "name": "Jingyu Zhou",
        "username": "jzhou",
        "avatar_template": "/user_avatar/forums.foundationdb.org/jzhou/{size}/445_2.png",
        "created_at": "2023-11-29T23:03:45.205Z",
        "cooked": "<p>Thanks! I\u2019ve opened a <a href=\"https://github.com/apple/foundationdb/pull/11082\">PR</a> from your repo.</p>",
        "post_number": 2,
        "post_type": 1,
        "posts_count": 3,
        "updated_at": "2023-11-29T23:03:45.205Z",
        "reply_count": 0,
        "reply_to_post_number": null,
        "quote_count": 0,
        "incoming_link_count": 2,
        "reads": 10,
        "readers_count": 9,
        "score": 27.0,
        "yours": false,
        "topic_id": 4266,
        "topic_slug": "compilation-error-in-fdbbackup-filedecoder-actor-cpp",
        "display_username": "Jingyu Zhou",
        "primary_group_name": null,
        "flair_name": null,
        "flair_url": null,
        "flair_bg_color": null,
        "flair_color": null,
        "flair_group_id": null,
        "badges_granted": [],
        "version": 1,
        "can_edit": false,
        "can_delete": false,
        "can_recover": false,
        "can_see_hidden_post": false,
        "can_wiki": false,
        "link_counts": [
          {
            "url": "https://github.com/apple/foundationdb/pull/11082",
            "internal": false,
            "reflection": false,
            "title": "To fix the fcntl2.h error, add the third parameter by jzhou77 \u00b7 Pull Request #11082 \u00b7 apple/foundationdb \u00b7 GitHub",
            "clicks": 0
          }
        ],
        "read": true,
        "user_title": null,
        "bookmarked": false,
        "actions_summary": [
          {
            "id": 2,
            "count": 1
          }
        ],
        "moderator": true,
        "admin": true,
        "staff": true,
        "user_id": 454,
        "hidden": false,
        "trust_level": 2,
        "deleted_at": null,
        "user_deleted": false,
        "edit_reason": null,
        "can_view_edit_history": true,
        "wiki": false,
        "post_url": "/t/compilation-error-in-fdbbackup-filedecoder-actor-cpp/4266/2",
        "can_accept_answer": false,
        "can_unaccept_answer": false,
        "accepted_answer": false,
        "topic_accepted_answer": null
      },
      {
        "id": 13566,
        "name": "",
        "username": "uvatbc",
        "avatar_template": "https://avatars.discourse-cdn.com/v4/letter/u/e274bd/{size}.png",
        "created_at": "2023-11-30T15:14:19.269Z",
        "cooked": "<p>Thanks so much!<br>\nMain compiles successfully now.</p>",
        "post_number": 3,
        "post_type": 1,
        "posts_count": 3,
        "updated_at": "2023-11-30T15:14:19.269Z",
        "reply_count": 0,
        "reply_to_post_number": null,
        "quote_count": 0,
        "incoming_link_count": 0,
        "reads": 9,
        "readers_count": 8,
        "score": 1.8,
        "yours": false,
        "topic_id": 4266,
        "topic_slug": "compilation-error-in-fdbbackup-filedecoder-actor-cpp",
        "display_username": "",
        "primary_group_name": null,
        "flair_name": null,
        "flair_url": null,
        "flair_bg_color": null,
        "flair_color": null,
        "flair_group_id": null,
        "badges_granted": [],
        "version": 1,
        "can_edit": false,
        "can_delete": false,
        "can_recover": false,
        "can_see_hidden_post": false,
        "can_wiki": false,
        "read": true,
        "user_title": null,
        "bookmarked": false,
        "actions_summary": [],
        "moderator": false,
        "admin": false,
        "staff": false,
        "user_id": 1354,
        "hidden": false,
        "trust_level": 0,
        "deleted_at": null,
        "user_deleted": false,
        "edit_reason": null,
        "can_view_edit_history": true,
        "wiki": false,
        "post_url": "/t/compilation-error-in-fdbbackup-filedecoder-actor-cpp/4266/3",
        "can_accept_answer": false,
        "can_unaccept_answer": false,
        "accepted_answer": false,
        "topic_accepted_answer": null
      }
    ],
    "stream": [
      13558,
      13559,
      13566
    ]
  },
  "timeline_lookup": [
    [
      1,
      692
    ],
    [
      3,
      691
    ]
  ],
  "suggested_topics": [],
  "tags": [],
  "tags_descriptions": {},
  "fancy_title": "Compilation error in fdbbackup/FileDecoder.actor.cpp",
  "id": 4266,
  "title": "Compilation error in fdbbackup/FileDecoder.actor.cpp",
  "posts_count": 3,
  "created_at": "2023-11-29T22:30:12.320Z",
  "views": 145,
  "reply_count": 0,
  "like_count": 1,
  "last_posted_at": "2023-11-30T15:14:19.269Z",
  "visible": true,
  "closed": false,
  "archived": false,
  "has_summary": false,
  "archetype": "regular",
  "slug": "compilation-error-in-fdbbackup-filedecoder-actor-cpp",
  "category_id": 5,
  "word_count": 223,
  "deleted_at": null,
  "user_id": 1354,
  "featured_link": null,
  "pinned_globally": false,
  "pinned_at": null,
  "pinned_until": null,
  "image_url": null,
  "slow_mode_seconds": 0,
  "draft": null,
  "draft_key": "topic_4266",
  "draft_sequence": null,
  "unpinned": null,
  "pinned": false,
  "current_post_number": 1,
  "highest_post_number": 3,
  "deleted_by": null,
  "actions_summary": [
    {
      "id": 4,
      "count": 0,
      "hidden": false,
      "can_act": false
    },
    {
      "id": 8,
      "count": 0,
      "hidden": false,
      "can_act": false
    },
    {
      "id": 10,
      "count": 0,
      "hidden": false,
      "can_act": false
    },
    {
      "id": 7,
      "count": 0,
      "hidden": false,
      "can_act": false
    }
  ],
  "chunk_size": 20,
  "bookmarked": false,
  "topic_timer": null,
  "message_bus_last_id": 0,
  "participant_count": 2,
  "show_read_indicator": false,
  "thumbnails": null,
  "slow_mode_enabled_until": null,
  "tags_disable_ads": false,
  "related_topics": [
    {
      "fancy_title": "Fresh install on Windows fails with FileOpenError `Must be unbuffered` when attempting to open &lsquo;xxxx-0.fdq&rsquo; file",
      "id": 496,
      "title": "Fresh install on Windows fails with FileOpenError `Must be unbuffered` when attempting to open 'xxxx-0.fdq' file",
      "slug": "fresh-install-on-windows-fails-with-fileopenerror-must-be-unbuffered-when-attempting-to-open-xxxx-0-fdq-file",
      "posts_count": 15,
      "reply_count": 6,
      "highest_post_number": 15,
      "image_url": "https://global.discourse-cdn.com/foundationdb/original/1X/a938a2538369b70a6d6a27cc8eca865311a7c245.png",
      "created_at": "2018-06-07T14:40:00.221Z",
      "last_posted_at": "2019-04-02T09:06:38.608Z",
      "bumped": true,
      "bumped_at": "2019-04-02T09:06:38.608Z",
      "archetype": "regular",
      "unseen": false,
      "pinned": false,
      "unpinned": null,
      "visible": true,
      "closed": false,
      "archived": false,
      "bookmarked": null,
      "liked": null,
      "tags": [],
      "tags_descriptions": {},
      "like_count": 2,
      "views": 1731,
      "category_id": 7,
      "featured_link": null,
      "has_accepted_answer": false,
      "posters": [
        {
          "extras": "latest",
          "description": "Original Poster, Most Recent Poster",
          "user": {
            "id": 53,
            "username": "KrzysFR",
            "name": "Christophe Chevalier",
            "avatar_template": "/user_avatar/forums.foundationdb.org/krzysfr/{size}/43_2.png",
            "trust_level": 2
          }
        },
        {
          "extras": null,
          "description": "Frequent Poster",
          "user": {
            "id": 13,
            "username": "alexmiller",
            "name": "Alex Miller",
            "avatar_template": "/user_avatar/forums.foundationdb.org/alexmiller/{size}/326_2.png",
            "trust_level": 4
          }
        },
        {
          "extras": null,
          "description": "Frequent Poster",
          "user": {
            "id": 337,
            "username": "mengxu",
            "name": "Meng Xu",
            "avatar_template": "/user_avatar/forums.foundationdb.org/mengxu/{size}/893_2.png",
            "trust_level": 2
          }
        }
      ]
    },
    {
      "fancy_title": "[RESOLVED?] Fdbbackup &lsquo;Platform error&rsquo; on &lsquo;file_backup_write_range&rsquo;",
      "id": 412,
      "title": "[RESOLVED?] Fdbbackup 'Platform error' on 'file_backup_write_range'",
      "slug": "resolved-fdbbackup-platform-error-on-file-backup-write-range",
      "posts_count": 9,
      "reply_count": 6,
      "highest_post_number": 9,
      "image_url": null,
      "created_at": "2018-05-14T13:43:20.133Z",
      "last_posted_at": "2018-05-17T00:24:36.294Z",
      "bumped": true,
      "bumped_at": "2018-05-17T00:24:36.294Z",
      "archetype": "regular",
      "unseen": false,
      "pinned": false,
      "unpinned": null,
      "visible": true,
      "closed": false,
      "archived": false,
      "bookmarked": null,
      "liked": null,
      "tags": [],
      "tags_descriptions": {},
      "like_count": 1,
      "views": 2465,
      "category_id": 7,
      "featured_link": null,
      "has_accepted_answer": false,
      "posters": [
        {
          "extras": "latest",
          "description": "Original Poster, Most Recent Poster",
          "user": {
            "id": 187,
            "username": "hiroshi",
            "name": "",
            "avatar_template": "/user_avatar/forums.foundationdb.org/hiroshi/{size}/147_2.png",
            "trust_level": 1
          }
        },
        {
          "extras": null,
          "description": "Frequent Poster",
          "user": {
            "id": 12,
            "username": "ajbeamon",
            "name": "A.J. Beamon",
            "avatar_template": "/user_avatar/forums.foundationdb.org/ajbeamon/{size}/13_2.png",
            "admin": true,
            "trust_level": 4
          }
        },
        {
          "extras": null,
          "description": "Frequent Poster",
          "user": {
            "id": 7,
            "username": "SteavedHams",
            "name": "Steve Atherton",
            "avatar_template": "/user_avatar/forums.foundationdb.org/steavedhams/{size}/18_2.png",
            "trust_level": 4
          }
        }
      ]
    },
    {
      "fancy_title": "How to complie and debug FDB (on mac os)?",
      "id": 176,
      "title": "How to complie and debug FDB (on mac os)?",
      "slug": "how-to-complie-and-debug-fdb-on-mac-os",
      "posts_count": 12,
      "reply_count": 7,
      "highest_post_number": 12,
      "image_url": null,
      "created_at": "2018-04-21T14:09:00.980Z",
      "last_posted_at": "2018-05-17T21:06:56.719Z",
      "bumped": true,
      "bumped_at": "2018-05-17T21:06:56.719Z",
      "archetype": "regular",
      "unseen": false,
      "pinned": false,
      "unpinned": null,
      "visible": true,
      "closed": false,
      "archived": false,
      "bookmarked": null,
      "liked": null,
      "tags": [],
      "tags_descriptions": {},
      "like_count": 1,
      "views": 2930,
      "category_id": 5,
      "featured_link": null,
      "has_accepted_answer": false,
      "posters": [
        {
          "extras": null,
          "description": "Original Poster",
          "user": {
            "id": 127,
            "username": "Johnny-Three",
            "name": "inolddays",
            "avatar_template": "/user_avatar/forums.foundationdb.org/johnny-three/{size}/111_2.png",
            "trust_level": 0
          }
        },
        {
          "extras": null,
          "description": "Frequent Poster",
          "user": {
            "id": 30,
            "username": "wwilson",
            "name": "Will Wilson",
            "avatar_template": "/user_avatar/forums.foundationdb.org/wwilson/{size}/88_2.png",
            "trust_level": 2
          }
        },
        {
          "extras": null,
          "description": "Frequent Poster",
          "user": {
            "id": 65,
            "username": "dougnukem",
            "name": "Doug Daniels",
            "avatar_template": "/user_avatar/forums.foundationdb.org/dougnukem/{size}/48_2.png",
            "trust_level": 1
          }
        },
        {
          "extras": null,
          "description": "Frequent Poster",
          "user": {
            "id": 8,
            "username": "alloc",
            "name": "Alec Grieser",
            "avatar_template": "/user_avatar/forums.foundationdb.org/alloc/{size}/9_2.png",
            "trust_level": 4
          }
        },
        {
          "extras": "latest",
          "description": "Most Recent Poster",
          "user": {
            "id": 13,
            "username": "alexmiller",
            "name": "Alex Miller",
            "avatar_template": "/user_avatar/forums.foundationdb.org/alexmiller/{size}/326_2.png",
            "trust_level": 4
          }
        }
      ]
    },
    {
      "fancy_title": "CMake and better IDE support",
      "id": 334,
      "title": "CMake and better IDE support",
      "slug": "cmake-and-better-ide-support",
      "posts_count": 10,
      "reply_count": 5,
      "highest_post_number": 10,
      "image_url": null,
      "created_at": "2018-05-03T23:09:33.328Z",
      "last_posted_at": "2018-08-11T00:35:30.260Z",
      "bumped": true,
      "bumped_at": "2018-08-11T00:35:30.260Z",
      "archetype": "regular",
      "unseen": false,
      "pinned": false,
      "unpinned": null,
      "visible": true,
      "closed": false,
      "archived": false,
      "bookmarked": null,
      "liked": null,
      "tags": [],
      "tags_descriptions": {},
      "like_count": 6,
      "views": 1711,
      "category_id": 8,
      "featured_link": null,
      "has_accepted_answer": false,
      "posters": [
        {
          "extras": null,
          "description": "Original Poster",
          "user": {
            "id": 15,
            "username": "markus.pilman",
            "name": "Markus Pilman",
            "avatar_template": "/user_avatar/forums.foundationdb.org/markus.pilman/{size}/379_2.png",
            "admin": true,
            "trust_level": 4
          }
        },
        {
          "extras": null,
          "description": "Frequent Poster",
          "user": {
            "id": 12,
            "username": "ajbeamon",
            "name": "A.J. Beamon",
            "avatar_template": "/user_avatar/forums.foundationdb.org/ajbeamon/{size}/13_2.png",
            "admin": true,
            "trust_level": 4
          }
        },
        {
          "extras": null,
          "description": "Frequent Poster",
          "user": {
            "id": 22,
            "username": "dave",
            "name": "David Scherer",
            "avatar_template": "/user_avatar/forums.foundationdb.org/dave/{size}/89_2.png",
            "trust_level": 1
          }
        },
        {
          "extras": "latest",
          "description": "Most Recent Poster",
          "user": {
            "id": 13,
            "username": "alexmiller",
            "name": "Alex Miller",
            "avatar_template": "/user_avatar/forums.foundationdb.org/alexmiller/{size}/326_2.png",
            "trust_level": 4
          }
        }
      ]
    },
    {
      "fancy_title": "Compiling on Linux with anything other than Ubuntu 15.04 / docker possible?",
      "id": 118,
      "title": "Compiling on Linux with anything other than Ubuntu 15.04 / docker possible?",
      "slug": "compiling-on-linux-with-anything-other-than-ubuntu-15-04-docker-possible",
      "posts_count": 6,
      "reply_count": 2,
      "highest_post_number": 6,
      "image_url": null,
      "created_at": "2018-04-20T11:21:20.195Z",
      "last_posted_at": "2018-04-23T01:06:08.039Z",
      "bumped": true,
      "bumped_at": "2018-04-23T01:06:08.039Z",
      "archetype": "regular",
      "unseen": false,
      "pinned": false,
      "unpinned": null,
      "visible": true,
      "closed": false,
      "archived": false,
      "bookmarked": null,
      "liked": null,
      "tags": [],
      "tags_descriptions": {},
      "like_count": 0,
      "views": 1149,
      "category_id": 8,
      "featured_link": null,
      "has_accepted_answer": false,
      "posters": [
        {
          "extras": null,
          "description": "Original Poster",
          "user": {
            "id": 77,
            "username": "Meai",
            "name": "Meai",
            "avatar_template": "/user_avatar/forums.foundationdb.org/meai/{size}/500_2.png",
            "trust_level": 1
          }
        },
        {
          "extras": null,
          "description": "Frequent Poster",
          "user": {
            "id": 78,
            "username": "pineapple",
            "name": "Brian Haslet",
            "avatar_template": "https://avatars.discourse-cdn.com/v4/letter/p/7993a0/{size}.png",
            "trust_level": 1
          }
        },
        {
          "extras": null,
          "description": "Frequent Poster",
          "user": {
            "id": 13,
            "username": "alexmiller",
            "name": "Alex Miller",
            "avatar_template": "/user_avatar/forums.foundationdb.org/alexmiller/{size}/326_2.png",
            "trust_level": 4
          }
        },
        {
          "extras": "latest",
          "description": "Most Recent Poster",
          "user": {
            "id": 30,
            "username": "wwilson",
            "name": "Will Wilson",
            "avatar_template": "/user_avatar/forums.foundationdb.org/wwilson/{size}/88_2.png",
            "trust_level": 2
          }
        }
      ]
    }
  ],
  "summarizable": false,
  "can_vote": false,
  "vote_count": 0,
  "user_voted": false,
  "discourse_zendesk_plugin_zendesk_id": null,
  "discourse_zendesk_plugin_zendesk_url": "https://your-url.zendesk.com/agent/tickets/",
  "details": {
    "can_edit": false,
    "notification_level": 1,
    "participants": [
      {
        "id": 1354,
        "username": "uvatbc",
        "name": "",
        "avatar_template": "https://avatars.discourse-cdn.com/v4/letter/u/e274bd/{size}.png",
        "post_count": 2,
        "primary_group_name": null,
        "flair_name": null,
        "flair_url": null,
        "flair_color": null,
        "flair_bg_color": null,
        "flair_group_id": null,
        "trust_level": 0
      },
      {
        "id": 454,
        "username": "jzhou",
        "name": "Jingyu Zhou",
        "avatar_template": "/user_avatar/forums.foundationdb.org/jzhou/{size}/445_2.png",
        "post_count": 1,
        "primary_group_name": null,
        "flair_name": null,
        "flair_url": null,
        "flair_color": null,
        "flair_bg_color": null,
        "flair_group_id": null,
        "admin": true,
        "moderator": true,
        "trust_level": 2
      }
    ],
    "created_by": {
      "id": 1354,
      "username": "uvatbc",
      "name": "",
      "avatar_template": "https://avatars.discourse-cdn.com/v4/letter/u/e274bd/{size}.png"
    },
    "last_poster": {
      "id": 1354,
      "username": "uvatbc",
      "name": "",
      "avatar_template": "https://avatars.discourse-cdn.com/v4/letter/u/e274bd/{size}.png"
    },
    "links": [
      {
        "url": "https://github.com/uvatbc/foundationdb",
        "title": "GitHub - uvatbc/foundationdb: FoundationDB - the open source, distributed, transactional key-value store",
        "internal": false,
        "attachment": false,
        "reflection": false,
        "clicks": 2,
        "user_id": 1354,
        "domain": "github.com",
        "root_domain": "github.com"
      }
    ]
  },
  "bookmarks": []
}